acme/__init__.py
acme/backend.py
acme/dask_helpers.py
acme/frontend.py
acme/logger.py
acme/shared.py
acme/spy_interface.py
esi_acme-2025.6.data/data/acme/CHANGELOG.md
esi_acme-2025.6.data/data/acme/CITATION.cff
esi_acme-2025.6.data/data/acme/LICENSE
esi_acme-2025.6.data/data/acme/README.md
esi_acme-2025.6.data/data/acme/tox.ini
esi_acme-2025.6.dist-info/licenses/LICENSES/BSD-3-Clause.txt
esi_acme-2025.6.dist-info/licenses/LICENSES/CC-BY-NC-ND-1.0.txt
esi_acme-2025.6.dist-info/licenses/LICENSES/CC-BY-NC-SA-1.0.txt
esi_acme-2025.6.dist-info/licenses/LICENSES/CC0-1.0.txt
esi_acme-2025.6.dist-info/METADATA
esi_acme-2025.6.dist-info/WHEEL
esi_acme-2025.6.dist-info/top_level.txt
esi_acme-2025.6.dist-info/RECORD
