Metadata-Version: 2.4
Name: esi-acme
Version: 2025.6
Summary: Asynchronous Computing Made ESI
Home-page: https://esi-acme.readthedocs.io/en/latest/
Author: Ernst Strüngmann Institute (ESI) for Neuroscience in Cooperation with Max Planck Society
Author-email: it@esi-frankfurt.de
License: BSD-3
Project-URL: Bug Tracker, https://github.com/esi-neuroscience/acme/issues
Project-URL: Documentation, https://esi-acme.readthedocs.io/en/latest/
Project-URL: Source Code, https://github.com/esi-neuroscience/acme
Classifier: Development Status :: 5 - Production/Stable
Classifier: Environment :: Console
Classifier: Intended Audience :: Science/Research
Classifier: Operating System :: OS Independent
Classifier: Programming Language :: Python
Classifier: Programming Language :: Python :: 3
Classifier: Programming Language :: Python :: 3.8
Classifier: Programming Language :: Python :: 3.9
Classifier: Programming Language :: Python :: 3.10
Classifier: Programming Language :: Python :: 3.11
Classifier: Programming Language :: Python :: 3.12
Classifier: Programming Language :: Python :: 3.13
Classifier: Programming Language :: Python :: Implementation :: CPython
Requires-Python: <3.14,>=3.8
License-File: LICENSES/BSD-3-Clause.txt
License-File: LICENSES/CC-BY-NC-ND-1.0.txt
License-File: LICENSES/CC-BY-NC-SA-1.0.txt
License-File: LICENSES/CC0-1.0.txt
Requires-Dist: cloudpickle>2.2
Requires-Dist: dask<=2025.5.1,>=2022.12.1
Requires-Dist: dask-jobqueue<1.0,>=0.8
Requires-Dist: h5py<4,>=3
Requires-Dist: numpy<3.0,>=1.0
Requires-Dist: toolz>=0.12
Requires-Dist: tqdm>=4.31
Provides-Extra: dev
Requires-Dist: ipdb; extra == "dev"
Requires-Dist: ipython<10.0; extra == "dev"
Requires-Dist: scipy<2.0,>=1.5; extra == "dev"
Requires-Dist: mypy; extra == "dev"
Requires-Dist: numpydoc; extra == "dev"
Requires-Dist: pytest-cov; extra == "dev"
Requires-Dist: reuse; extra == "dev"
Requires-Dist: sphinx; extra == "dev"
Requires-Dist: sphinx_automodapi; extra == "dev"
Requires-Dist: sphinx_bootstrap_theme<0.8; extra == "dev"
Requires-Dist: sphinx-tabs; extra == "dev"
Requires-Dist: tox; extra == "dev"
Dynamic: license-file
